mlmechanica/__init__.py
mlmechanica/regression/__init__.py
mlmechanica/regression/linear/__init__.py
mlmechanica/regression/linear/lasso.py
mlmechanica/regression/linear/multiple.py
mlmechanica/regression/linear/ridge.py
mlmechanica/regression/linear/simple.py
mlmechanica-0.1.0.dist-info/licenses/LICENSE
mlmechanica-0.1.0.dist-info/METADATA
mlmechanica-0.1.0.dist-info/WHEEL
mlmechanica-0.1.0.dist-info/top_level.txt
mlmechanica-0.1.0.dist-info/RECORD
