Metadata-Version: 2.4
Name: mlmechanica
Version: 0.1.0
Summary: A transparent, 'Glass Box' Machine Learning library designed for education.
Author-email: Sarbik Mal <sarbikjob1999@gmail.com>
License: MIT License
Project-URL: Homepage, https://github.com/Sarbik-Mal/mlmechanica
Keywords: machine learning,education,linear regression,transparent ai,numpy
Classifier: Development Status :: 3 - Alpha
Classifier: Intended Audience :: Education
Classifier: Intended Audience :: Developers
Classifier: License :: OSI Approved :: MIT License
Classifier: Programming Language :: Python :: 3
Classifier: Programming Language :: Python :: 3.9
Classifier: Programming Language :: Python :: 3.10
Classifier: Programming Language :: Python :: 3.11
Classifier: Programming Language :: Python :: 3.12
Classifier: Programming Language :: Python :: 3.13
Classifier: Topic :: Scientific/Engineering :: Artificial Intelligence
Requires-Python: >=3.9
License-File: LICENSE
Requires-Dist: numpy>=1.21.0
Requires-Dist: scipy>=1.7.0
Requires-Dist: scikit-learn>=1.0.0
Dynamic: license-file
